{
  "version": 1,
  "skills": {
    "self-improving-agent": {
      "name": "self-improving-agent",
      "zip_url": "https://lightmake.site/api/v1/download?slug=self-improving-agent",
      "source": "skillhub",
      "version": "1.0.11"
    },
    "skill-vetter": {
      "name": "Skill Vetter",
      "zip_url": "https://lightmake.site/api/v1/download?slug=skill-vetter",
      "source": "skillhub",
      "version": "1.0.0"
    },
    "github": {
      "name": "Github",
      "zip_url": "https://lightmake.site/api/v1/download?slug=github",
      "source": "skillhub",
      "version": "1.0.0"
    },
    "tavily-search": {
      "name": "Tavily Web Search",
      "zip_url": "https://lightmake.site/api/v1/download?slug=tavily-search",
      "source": "skillhub",
      "version": "1.0.0"
    },
    "api-gateway": {
      "name": "API Gateway",
      "zip_url": "https://lightmake.site/api/v1/download?slug=api-gateway",
      "source": "skillhub",
      "version": "1.0.54"
    },
    "ai-ppt-generator": {
      "name": "Ai Ppt Generator",
      "zip_url": "https://lightmake.site/api/v1/download?slug=ai-ppt-generator",
      "source": "skillhub",
      "version": "1.1.2"
    },
    "document-pro": {
      "name": "Document Pro",
      "zip_url": "https://lightmake.site/api/v1/download?slug=document-pro",
      "source": "skillhub",
      "version": "1.0.0"
    }
  }
}
